ecmc_scraper/__init__.py
ecmc_scraper/__main__.py
ecmc_scraper/config.py
ecmc_scraper/const.py
ecmc_scraper/convert_production_summaries_access_to_parquet.py
ecmc_scraper/enum.py
ecmc_scraper/log_config.yaml
ecmc_scraper/logger.py
ecmc_scraper/main.py
ecmc_scraper/scrape_production_summaries.py
ecmc_scraper/transform_production_summaries.py
ecmc_scraper/utils.py
ecmc_scraper-0.2.1.dist-info/entry_points.txt
ecmc_scraper-0.2.1.dist-info/LICENSE
ecmc_scraper-0.2.1.dist-info/METADATA
ecmc_scraper-0.2.1.dist-info/WHEEL
ecmc_scraper-0.2.1.dist-info/RECORD
