Metadata-Version: 2.1
Name: ecmc-scraper
Version: 0.2.1
Summary: Scrapes the ECMC download page. Includes transform scripts used by CDPHE OIP team.
Author: John Evans
Author-email: john.p.evans@state.co.us
Requires-Python: >=3.9,<4.0
Classifier: Programming Language :: Python :: 3
Classifier: Programming Language :: Python :: 3.9
Classifier: Programming Language :: Python :: 3.10
Classifier: Programming Language :: Python :: 3.11
Classifier: Programming Language :: Python :: 3.12
Requires-Dist: arrow-odbc (>=4.0.0,<5.0.0)
Requires-Dist: polars (>=0.20.7,<0.21.0)
Requires-Dist: pyyaml (>=6.0.1,<7.0.0)
Requires-Dist: requests (>=2.31.0,<3.0.0)
Requires-Dist: typer[all] (>=0.12.3,<0.13.0)
